pyams_catalog/__init__.py
pyams_catalog/events.py
pyams_catalog/i18n.py
pyams_catalog/include.py
pyams_catalog/index.py
pyams_catalog/interfaces.py
pyams_catalog/nltk.py
pyams_catalog/query.py
pyams_catalog/testing.py
pyams_catalog/utils.py
pyams_catalog/doctests/README.rst
pyams_catalog/generations/__init__.py
pyams_catalog/locales/pyams_catalog.pot
pyams_catalog/locales/fr/LC_MESSAGES/pyams_catalog.mo
pyams_catalog/locales/fr/LC_MESSAGES/pyams_catalog.po
pyams_catalog/scripts/__init__.py
pyams_catalog/tests/__init__.py
pyams_catalog/tests/test_utilsdocs.py
pyams_catalog/tests/test_utilsdocstrings.py
pyams_catalog/zmi/__init__.py
pyams_catalog-2.2.2.dist-info/LICENSE
pyams_catalog-2.2.2.dist-info/METADATA
pyams_catalog-2.2.2.dist-info/WHEEL
pyams_catalog-2.2.2.dist-info/entry_points.txt
pyams_catalog-2.2.2.dist-info/namespace_packages.txt
pyams_catalog-2.2.2.dist-info/top_level.txt
pyams_catalog-2.2.2.dist-info/RECORD
