Metadata-Version: 2.1
Name: pyams-catalog
Version: 2.2.2
Summary: PyAMS extensions for Hypatia catalog
Home-page: https://pyams.readthedocs.io
Author: Thierry Florac
Author-email: tflorac@ulthar.net
License: ZPL
Keywords: Pyramid PyAMS
Classifier: License :: OSI Approved :: Zope Public License
Classifier: Development Status :: 4 - Beta
Classifier: Programming Language :: Python
Classifier: Framework :: Pyramid
Classifier: Topic :: Software Development :: Libraries :: Python Modules
Requires-Python: >=3.7
License-File: LICENSE
Requires-Dist: setuptools
Requires-Dist: ZODB
Requires-Dist: hypatia
Requires-Dist: nltk >=3.5
Requires-Dist: persistent
Requires-Dist: pyams-i18n
Requires-Dist: pyams-site
Requires-Dist: pyams-utils >=2.2.0
Requires-Dist: pyramid >=2.0.0
Requires-Dist: transaction
Requires-Dist: zodbupdate
Requires-Dist: zope.interface
Requires-Dist: zope.intid
Requires-Dist: zope.keyreference
Requires-Dist: zope.lifecycleevent
Provides-Extra: test
Requires-Dist: pyams-zmi ; extra == 'test'
Requires-Dist: pyramid-zcml ; extra == 'test'
Requires-Dist: zope.exceptions ; extra == 'test'
